[
    {
        "identity": "trainer",
        "model_info": {
            "name": "vertical_kmeans"
        },
        "input": {
            "trainset": [
                {
                    "type": "csv",
                    "path": "./dataset/breast_cancer_wisconsin_vertical/2party",
                    "name": "breast_cancer_wisconsin_vertical_1_train.csv",
                    "has_label": false,
                    "has_id": true
                }
            ]
        },
        "output": {
            "path": "/opt/checkpoints/[JOB_ID]/[NODE_ID]",
            "model": {
                "name": "vertical_kmeans_[STAGE_ID].pkl"
            },
            "result": {
                "name": "cluster_result_[STAGE_ID].csv"
            },
            "summary": {
                "name": "cluster_summary_[STAGE_ID].csv"
            }
        },
        "train_info": {
        }
    }
]